msvdd_bloc/__init__.py
msvdd_bloc/about.py
msvdd_bloc/fileio.py
msvdd_bloc/regexes.py
msvdd_bloc/schemas.py
msvdd_bloc/tokenize.py
msvdd_bloc/utils.py
msvdd_bloc/job_postings/__init__.py
msvdd_bloc/job_postings/fetch.py
msvdd_bloc/job_postings/munge.py
msvdd_bloc/resumes/__init__.py
msvdd_bloc/resumes/augment_utils.py
msvdd_bloc/resumes/constants.py
msvdd_bloc/resumes/extract.py
msvdd_bloc/resumes/generate_utils.py
msvdd_bloc/resumes/munge.py
msvdd_bloc/resumes/parse.py
msvdd_bloc/resumes/parse_utils.py
msvdd_bloc/resumes/segment.py
msvdd_bloc/resumes/basics/__init__.py
msvdd_bloc/resumes/basics/augment.py
msvdd_bloc/resumes/basics/constants.py
msvdd_bloc/resumes/basics/generate.py
msvdd_bloc/resumes/basics/parse.py
msvdd_bloc/resumes/education/__init__.py
msvdd_bloc/resumes/education/augment.py
msvdd_bloc/resumes/education/constants.py
msvdd_bloc/resumes/education/generate.py
msvdd_bloc/resumes/education/parse.py
msvdd_bloc/resumes/skills/__init__.py
msvdd_bloc/resumes/skills/augment.py
msvdd_bloc/resumes/skills/constants.py
msvdd_bloc/resumes/skills/generate.py
msvdd_bloc/resumes/skills/parse.py
msvdd_bloc/resumes/work/__init__.py
msvdd_bloc/resumes/work/augment.py
msvdd_bloc/resumes/work/constants.py
msvdd_bloc/resumes/work/generate.py
msvdd_bloc/resumes/work/parse.py
hiphopscrap-0.1.1.dist-info/METADATA
hiphopscrap-0.1.1.dist-info/WHEEL
hiphopscrap-0.1.1.dist-info/top_level.txt
hiphopscrap-0.1.1.dist-info/RECORD
