Metadata-Version: 2.1
Name: hiphopscrap
Version: 0.1.1
Summary: fetch, munge, and parse résumés and job postings
Home-page: https://github.com/datakind/msvdd_Bloc
Maintainer: Burton DeWilde
Maintainer-email: burtdewilde@gmail.com
License: UNKNOWN
Platform: UNKNOWN
Classifier: Development Status :: 4 - Beta
Classifier: Intended Audience :: Developers
Classifier: Programming Language :: Python
Classifier: Programming Language :: Python :: 3
Classifier: Programming Language :: Python :: 3.6
Classifier: Programming Language :: Python :: 3.7
Requires-Python: >=3.6
Requires-Dist: beautifulsoup4 (>=4.7.0)
Requires-Dist: Faker (>=2.0.0)
Requires-Dist: ftfy (>=5.6)
Requires-Dist: glom (>=19.0.0)
Requires-Dist: marshmallow (>=3.0.0)
Requires-Dist: matplotlib (>=3.0.0)
Requires-Dist: pandas (>=0.25.0)
Requires-Dist: probablepeople (>=0.5.4)
Requires-Dist: python-crfsuite (>=0.9.6)
Requires-Dist: requests (>=2.20.0)
Requires-Dist: spacy (<2.2,>=2.1)
Requires-Dist: textacy (>=0.9.0)
Requires-Dist: tika (>=1.19)
Requires-Dist: toolz (>=0.10.0)
Requires-Dist: usaddress (>=0.5.10)
Requires-Dist: watermark (>=1.8.0)
Requires-Dist: yapdfminer (>=1.2.0)
